APEC/__init__.py
APEC/clustering.py
APEC/convert.py
APEC/generate.py
APEC/plot.py
APEC-1.2.2.dist-info/METADATA
APEC-1.2.2.dist-info/WHEEL
APEC-1.2.2.dist-info/top_level.txt
APEC-1.2.2.dist-info/RECORD
