Metadata-Version: 2.1
Name: APEC
Version: 1.2.2
Summary: Single cell epigenomic clustering based on accessibility pattern
Home-page: https://github.com/QuKunLab/APEC
Author: Bin Li
Author-email: libinsnet@gmail.com
License: BSD License
Platform: all
Classifier: Development Status :: 4 - Beta
Classifier: Operating System :: OS Independent
Classifier: Intended Audience :: Developers
Classifier: License :: OSI Approved :: BSD License
Classifier: Programming Language :: Python :: 3.6
Classifier: Topic :: Scientific/Engineering :: Bio-Informatics
Requires-Dist: numpy (==1.16.2)
Requires-Dist: scipy (==1.0.0)
Requires-Dist: pandas (==0.24.2)
Requires-Dist: matplotlib (==3.0.3)
Requires-Dist: seaborn (==0.9.0)
Requires-Dist: numba (==0.43.1)
Requires-Dist: networkx (==2.2)
Requires-Dist: python-louvain (==0.11)
Requires-Dist: scikit-learn (==0.20.0)
Requires-Dist: MulticoreTsne (==0.1)
Requires-Dist: umap-learn (==0.3.8)
Requires-Dist: rpy2 (==2.8.5)
Requires-Dist: setuptools
